buildingsync_asset_extractor/__init__.py
buildingsync_asset_extractor/bae_types.py
buildingsync_asset_extractor/config/asset_definitions.json
buildingsync_asset_extractor/converter.py
buildingsync_asset_extractor/cts/CTS Comprehensive Evaluation Upload Template_20240312_021125.xlsx
buildingsync_asset_extractor/cts/__init__.py
buildingsync_asset_extractor/cts/classes.py
buildingsync_asset_extractor/cts/cts.py
buildingsync_asset_extractor/cts/cts_map.md
buildingsync_asset_extractor/cts/energy_and_water_conservation_measures.py
buildingsync_asset_extractor/cts/measure_type_to_cts_field.py
buildingsync_asset_extractor/cts/parsers.py
buildingsync_asset_extractor/cts_main.py
buildingsync_asset_extractor/eletric_fuel_types.py
buildingsync_asset_extractor/errors.py
buildingsync_asset_extractor/formatters.py
buildingsync_asset_extractor/lighting_processing/building_occ_class_to_building_type.py
buildingsync_asset_extractor/lighting_processing/building_space_type_to_lpd.py
buildingsync_asset_extractor/lighting_processing/building_type_to_lpd.py
buildingsync_asset_extractor/lighting_processing/lighting_processing.py
buildingsync_asset_extractor/lighting_processing/section_occ_class_to_section_type.py
buildingsync_asset_extractor/main.py
buildingsync_asset_extractor/processor.py
buildingsync_asset_extractor/schemas/asset_definitions_schema.json
buildingsync_asset_extractor/schemas/extracted_assets_schema.json
buildingsync_asset_extractor-0.3.0.dist-info/licenses/LICENSE
buildingsync_asset_extractor-0.3.0.dist-info/WHEEL
buildingsync_asset_extractor-0.3.0.dist-info/METADATA
buildingsync_asset_extractor-0.3.0.dist-info/RECORD
