Metadata-Version: 2.4
Name: buildingsync-asset-extractor
Version: 0.3.0
Summary: BuildingSync Asset Extractor (BAE)
Keywords: BuildingSync,Building Data Exchange
Author: Katherine Fleming, Hannah Eslinger
Author-email: Katherine Fleming <katherine.fleming@nlr.gov>, Hannah Eslinger <hannah.eslinger@nlr.gov>
License-Expression: BSD-4-Clause
License-File: LICENSE
Classifier: Development Status :: 4 - Beta
Classifier: Intended Audience :: Developers
Classifier: Operating System :: OS Independent
Classifier: Programming Language :: Python :: 3
Classifier: Programming Language :: Python :: 3 :: Only
Classifier: Programming Language :: Python :: 3.10
Classifier: Programming Language :: Python :: 3.11
Classifier: Programming Language :: Python :: 3.12
Classifier: Programming Language :: Python :: 3.13
Classifier: Programming Language :: Python :: 3.14
Requires-Dist: lxml>=6.0.0,<7
Requires-Dist: pandas>=2.2.0,<3
Requires-Dist: styleframe>=4.2,<5
Requires-Python: >=3.10
